minerva/__init__.py
minerva/barcodes_to_kmer_documents.py
minerva/deconvolution/__init__.py
minerva/deconvolution/barcode_kmer_table.py
minerva/deconvolution/build_and_filter_table.py
minerva/deconvolution/cluster_matrix.py
minerva/deconvolution/deconvolve_barcodes.py
minerva/deconvolution/deconvolve_fasta.py
minerva/deconvolution/progress_bar.py
minerva/deconvolution/utils.py
minerva/eval/__init__.py
minerva/eval/annotate_fastq.py
minerva/eval/eval_deconvolution.py
minerva/gimmebio/__init__.py
minerva/gimmebio/fastx.py
minerva/gimmebio/kmers.py
minerva/gimmebio/readclouds.py
minerva/gimmebio/seqs.py
minerva/gimmebio/utils.py
minerva/kraken/__init__.py
minerva/kraken/enhance_kraken.py
minerva_deconvolve-1.1.3.dist-info/METADATA
minerva_deconvolve-1.1.3.dist-info/RECORD
minerva_deconvolve-1.1.3.dist-info/WHEEL
minerva_deconvolve-1.1.3.dist-info/entry_points.txt
minerva_deconvolve-1.1.3.dist-info/top_level.txt
tests/__init__.py
tests/test_sample.py
