Metadata-Version: 2.1
Name: minerva-deconvolve
Version: 1.1.3
Summary: Algorithm for deconvolving and clustering barcoded short reads
Home-page: https://github.com/dcdanko/minerva_barcode_deconvolution
Author: David C. Danko
Author-email: dcd3001@med.cornell.edu
License: UNKNOWN
Platform: UNKNOWN
Classifier: Development Status :: 5 - Production/Stable
Classifier: Programming Language :: Python :: 3
Classifier: Programming Language :: Python :: 3.4
Classifier: Programming Language :: Python :: 3.5
Requires-Dist: scikit-learn
Requires-Dist: numpy
Requires-Dist: pandas
Requires-Dist: scipy
Requires-Dist: click
Requires-Dist: argparse
